README.md
setup.py
tap_amazon_mws/__init__.py
tap_amazon_mws/cache.py
tap_amazon_mws/client.py
tap_amazon_mws/config.py
tap_amazon_mws/state.py
tap_amazon_mws.egg-info/PKG-INFO
tap_amazon_mws.egg-info/SOURCES.txt
tap_amazon_mws.egg-info/dependency_links.txt
tap_amazon_mws.egg-info/entry_points.txt
tap_amazon_mws.egg-info/requires.txt
tap_amazon_mws.egg-info/top_level.txt
tap_amazon_mws/schemas/inventory.json
tap_amazon_mws/schemas/orders.json
tap_amazon_mws/schemas/products.json
tap_amazon_mws/streams/__init__.py
tap_amazon_mws/streams/base.py
tap_amazon_mws/streams/inventory.py
tap_amazon_mws/streams/orders.py
tap_amazon_mws/streams/products.py