Metadata-Version: 1.1
Name: tap-amazon-mws
Version: 0.0.1
Summary: Singer.io tap for extracting data from the Amazon MWS API
Home-page: http://fishtownanalytics.com
Author: Fishtown Analytics
Author-email: UNKNOWN
License: UNKNOWN
Platform: UNKNOWN
Classifier: Programming Language :: Python :: 3 :: Only
